{"cameraMode":{"drawMode":0,"name":"Shaded","section":"Shading Mode"},"sceneLighting":true,"audioPlay":false,"sceneViewState":{"m_AlwaysRefresh":false,"showFog":true,"showSkybox":true,"showFlares":true,"showImageEffects":true,"showParticleSystems":true,"showVisualEffectGraphs":true,"m_FxEnabled":true},"in2DMode":false,"pivot":{"x":-5.6696672439575199,"y":-4.943532943725586,"z":-9.351486206054688},"rotation":{"x":-0.06406053900718689,"y":0.9345998764038086,"z":-0.2201218605041504,"w":-0.2719882130622864},"size":10.0,"orthographic":false}